DLMSCommunicationProfile/__init__.py
DLMSCommunicationProfile/base.py
DLMSCommunicationProfile/communication_profile.py
DLMSCommunicationProfile/limit.py
DLMSCommunicationProfile/osi.py
DLMSCommunicationProfile/py.typed
DLMSCommunicationProfile/HDLC/__init__.py
DLMSCommunicationProfile/HDLC/hdlc.py
DLMSCommunicationProfile/HDLC/negotiation.py
DLMSCommunicationProfile/MBUS/__init__.py
DLMSCommunicationProfile/MBUS/m_bus.py
DLMSCommunicationProfile/TCPUDPIP/__init__.py
DLMSCommunicationProfile/TCPUDPIP/tcp_udp_ip.py
dlmscommunicationprofile-0.1.12.dist-info/METADATA
dlmscommunicationprofile-0.1.12.dist-info/WHEEL
dlmscommunicationprofile-0.1.12.dist-info/top_level.txt
dlmscommunicationprofile-0.1.12.dist-info/RECORD
