Metadata-Version: 2.4
Name: DLMSCommunicationProfile
Version: 0.1.12
Summary: dlms-spodes
Author-email: Serj Kotilevski <youserj@outlook.com>
Keywords: dlms,greenbook
Classifier: Programming Language :: Python :: 3
Classifier: License :: OSI Approved :: MIT License
Classifier: Operating System :: OS Independent
Requires-Python: >=3.12
Requires-Dist: DLMS-SPODES<0.89,>=0.84
Provides-Extra: dev
Requires-Dist: mypy>=1.5.0; extra == "dev"
Requires-Dist: ruff>=0.11; extra == "dev"
Requires-Dist: types-requests; extra == "dev"
